odoo10_addon_quality_control-10.0.1.0.0-py2.7-nspkg.pth
odoo/addons/quality_control/README.rst
odoo/addons/quality_control/__init__.py
odoo/addons/quality_control/__manifest__.py
odoo/addons/quality_control/data/quality_control_data.xml
odoo/addons/quality_control/demo/quality_control_demo.xml
odoo/addons/quality_control/i18n/am.po
odoo/addons/quality_control/i18n/ar.po
odoo/addons/quality_control/i18n/bg.po
odoo/addons/quality_control/i18n/bs.po
odoo/addons/quality_control/i18n/ca.po
odoo/addons/quality_control/i18n/ca_ES.po
odoo/addons/quality_control/i18n/cs.po
odoo/addons/quality_control/i18n/da.po
odoo/addons/quality_control/i18n/de.po
odoo/addons/quality_control/i18n/el_GR.po
odoo/addons/quality_control/i18n/en_AU.po
odoo/addons/quality_control/i18n/en_GB.po
odoo/addons/quality_control/i18n/es.po
odoo/addons/quality_control/i18n/es_AR.po
odoo/addons/quality_control/i18n/es_CL.po
odoo/addons/quality_control/i18n/es_CO.po
odoo/addons/quality_control/i18n/es_CR.po
odoo/addons/quality_control/i18n/es_DO.po
odoo/addons/quality_control/i18n/es_EC.po
odoo/addons/quality_control/i18n/es_ES.po
odoo/addons/quality_control/i18n/es_MX.po
odoo/addons/quality_control/i18n/es_PE.po
odoo/addons/quality_control/i18n/es_PY.po
odoo/addons/quality_control/i18n/es_VE.po
odoo/addons/quality_control/i18n/et.po
odoo/addons/quality_control/i18n/eu.po
odoo/addons/quality_control/i18n/fa.po
odoo/addons/quality_control/i18n/fi.po
odoo/addons/quality_control/i18n/fr.po
odoo/addons/quality_control/i18n/fr_CA.po
odoo/addons/quality_control/i18n/fr_CH.po
odoo/addons/quality_control/i18n/fr_FR.po
odoo/addons/quality_control/i18n/gl.po
odoo/addons/quality_control/i18n/gl_ES.po
odoo/addons/quality_control/i18n/he.po
odoo/addons/quality_control/i18n/hi.po
odoo/addons/quality_control/i18n/hr.po
odoo/addons/quality_control/i18n/hr_HR.po
odoo/addons/quality_control/i18n/hu.po
odoo/addons/quality_control/i18n/id.po
odoo10_addon_quality_control-10.0.1.0.0.dist-info/DESCRIPTION.rst
odoo10_addon_quality_control-10.0.1.0.0.dist-info/METADATA
odoo10_addon_quality_control-10.0.1.0.0.dist-info/RECORD
odoo10_addon_quality_control-10.0.1.0.0.dist-info/WHEEL
odoo10_addon_quality_control-10.0.1.0.0.dist-info/metadata.json
odoo10_addon_quality_control-10.0.1.0.0.dist-info/namespace_packages.txt
odoo10_addon_quality_control-10.0.1.0.0.dist-info/top_level.txt
